gmic_sphinx/__init__.py
gmic_sphinx/gmicpic.py
gmic_sphinx/samples/sample_apples.png
gmic_sphinx/samples/sample_balloons.png
gmic_sphinx/samples/sample_barbara.png
gmic_sphinx/samples/sample_boats.png
gmic_sphinx/samples/sample_bottles.png
gmic_sphinx/samples/sample_butterfly.png
gmic_sphinx/samples/sample_cameraman.png
gmic_sphinx/samples/sample_car.png
gmic_sphinx/samples/sample_cat.png
gmic_sphinx/samples/sample_chick.png
gmic_sphinx/samples/sample_cliff.png
gmic_sphinx/samples/sample_colorful.png
gmic_sphinx/samples/sample_david.png
gmic_sphinx/samples/sample_dog.png
gmic_sphinx/samples/sample_duck.png
gmic_sphinx/samples/sample_eagle.png
gmic_sphinx/samples/sample_earth.png
gmic_sphinx/samples/sample_elephant.png
gmic_sphinx/samples/sample_flower.png
gmic_sphinx/samples/sample_fruits.png
gmic_sphinx/samples/sample_gmicky.png
gmic_sphinx/samples/sample_gmicky_mahvin.png
gmic_sphinx/samples/sample_gmicky_wilber.png
gmic_sphinx/samples/sample_greece.png
gmic_sphinx/samples/sample_gummy.png
gmic_sphinx/samples/sample_house.png
gmic_sphinx/samples/sample_inside.png
gmic_sphinx/samples/sample_landscape.png
gmic_sphinx/samples/sample_leaf.png
gmic_sphinx/samples/sample_lena.png
gmic_sphinx/samples/sample_leno.png
gmic_sphinx/samples/sample_lion.png
gmic_sphinx/samples/sample_mandrill.png
gmic_sphinx/samples/sample_monalisa.png
gmic_sphinx/samples/sample_monkey.png
gmic_sphinx/samples/sample_parrots.png
gmic_sphinx/samples/sample_pencils.png
gmic_sphinx/samples/sample_peppers.png
gmic_sphinx/samples/sample_portrait0.png
gmic_sphinx/samples/sample_portrait1.png
gmic_sphinx/samples/sample_portrait2.png
gmic_sphinx/samples/sample_portrait3.png
gmic_sphinx/samples/sample_portrait4.png
gmic_sphinx/samples/sample_portrait5.png
gmic_sphinx/samples/sample_portrait6.png
gmic_sphinx/samples/sample_portrait7.png
gmic_sphinx/samples/sample_portrait8.png
gmic_sphinx/samples/sample_portrait9.png
gmic_sphinx/samples/sample_roddy.png
gmic_sphinx/samples/sample_rooster.png
gmic_sphinx-0.0.4.dist-info/LICENSE
gmic_sphinx-0.0.4.dist-info/METADATA
gmic_sphinx-0.0.4.dist-info/WHEEL
gmic_sphinx-0.0.4.dist-info/top_level.txt
gmic_sphinx-0.0.4.dist-info/RECORD
