Metadata-Version: 2.1
Name: gmic-sphinx
Version: 0.0.4
Summary: A simple sphinx extension to generate images from G'MIC commands
Home-page: https://github.com/myselfhimself/gmic-sphinx
Author: Jonathan-David Schröder
Author-email: jonathan.schroder@gmail.com
License: UNKNOWN
Keywords: sphinx extension gmic image-processing
Platform: UNKNOWN
Classifier: Development Status :: 2 - Pre-Alpha
Classifier: Intended Audience :: Information Technology
Classifier: License :: OSI Approved :: CEA CNRS Inria Logiciel Libre License, version 2.1 (CeCILL-2.1)
Classifier: Programming Language :: Python
Classifier: Topic :: Utilities
Requires-Dist: sphinx
Requires-Dist: docutils
Requires-Dist: gmic
